LICENSE
MANIFEST.in
README.md
setup.py
carehttp/__init__.py
carehttp/__version__.py
carehttp/check_suffix.py
carehttp/core.py
carehttp/user_agents.py
carehttp.egg-info/PKG-INFO
carehttp.egg-info/SOURCES.txt
carehttp.egg-info/dependency_links.txt
carehttp.egg-info/requires.txt
carehttp.egg-info/top_level.txt