Metadata-Version: 2.1
Name: carehttp
Version: 0.3.10
Summary: Warp Requests with Retrying, so some important requests could easily retry when encounter error
Home-page: https://github.com/pgshow/carehttp
Author: Daniel
Author-email: me@example.com
License: MIT
Platform: UNKNOWN
Classifier: License :: OSI Approved :: MIT License
Classifier: Programming Language :: Python :: 3
Requires-Python: >=3.6.0
License-File: LICENSE
